repsim/__init__.py
repsim/_func_cca.py
repsim/_func_cka.py
repsim/_func_dot_product.py
repsim/_func_hsic.py
repsim/_func_pwcca.py
repsim/_func_repsim.py
repsim/_func_svcca.py
repsim/_repsim.cpython-312-darwin.so
repsim/_utils.py
repsim/_version.py
repsim-0.1.5.dist-info/METADATA
repsim-0.1.5.dist-info/WHEEL
repsim-0.1.5.dist-info/licenses/LICENSE
repsim-0.1.5.dist-info/RECORD
